sanic_json/__init__.py
sanic_json/middleware.py
sanic_json/sig.py
sanic_json/validate.py
sanic_json-0.1.13.dist-info/METADATA
sanic_json-0.1.13.dist-info/WHEEL
sanic_json-0.1.13.dist-info/top_level.txt
sanic_json-0.1.13.dist-info/RECORD
