Metadata-Version: 2.1
Name: sanic-json
Version: 0.1.13
Summary: Sanic framework thin wapper to write JSON API
Home-page: https://github.com/weaming/sanic-json
Author: weaming
Author-email: garden.yuen@gmail.com
License: UNKNOWN
Project-URL: Source, https://github.com/weaming/sanic-json
Project-URL: Bug Reports, https://github.com/weaming/sanic-json
Keywords: sanic json api
Platform: UNKNOWN
